fanuc_remote_buffer/__init__.py
fanuc_remote_buffer/cli.py
fanuc_remote_buffer/fanuc_remote_buffer.py
fanuc_remote_buffer/protocol.py
fanuc_remote_buffer-0.1.3.dist-info/DESCRIPTION.rst
fanuc_remote_buffer-0.1.3.dist-info/METADATA
fanuc_remote_buffer-0.1.3.dist-info/RECORD
fanuc_remote_buffer-0.1.3.dist-info/WHEEL
fanuc_remote_buffer-0.1.3.dist-info/metadata.json
fanuc_remote_buffer-0.1.3.dist-info/top_level.txt
