Metadata-Version: 2.0
Name: fanuc-remote-buffer
Version: 0.1.3
Summary: Fanuc Remote Buffer interface library
Home-page: https://gitlab.com/tanelikaivola/fanuc_remote_buffer
Author: Taneli Kaivola
Author-email: dist@ihme.org
License: MIT license
Keywords: fanuc_remote_buffer
Platform: UNKNOWN
Classifier: Development Status :: 2 - Pre-Alpha
Classifier: Intended Audience :: Developers
Classifier: License :: OSI Approved :: MIT License
Classifier: Natural Language :: English
Classifier: Programming Language :: Python :: 3.6
Classifier: Programming Language :: Python :: 3.7
Requires-Dist: Click (>=6.0)
Requires-Dist: construct (<2.10,>=2.9)
